[
    {
        "image_name": "img_0.png",
        "x": -7.259801864624023,
        "y": -16.370670318603516,
        "z": -5.467299461364746,
        "yaw": 0.0,
        "timestamp": "2026-03-05T18:05:03.176606"
    },
    {
        "image_name": "img_1.png",
        "x": -7.461750030517578,
        "y": -16.173412322998047,
        "z": -5.465950965881348,
        "yaw": 90.0,
        "timestamp": "2026-03-05T18:05:06.929737"
    },
    {
        "image_name": "img_2.png",
        "x": -7.462471961975098,
        "y": -16.174503326416016,
        "z": -5.467215538024902,
        "yaw": 180.0,
        "timestamp": "2026-03-05T18:05:10.674864"
    },
    {
        "image_name": "img_3.png",
        "x": -7.462471961975098,
        "y": -16.174503326416016,
        "z": -5.468027591705322,
        "yaw": 270.0,
        "timestamp": "2026-03-05T18:05:14.374436"
    },
    {
        "image_name": "img_4.png",
        "x": -11.8508882522583,
        "y": -12.156476020812988,
        "z": -5.482479095458984,
        "yaw": 0.0,
        "timestamp": "2026-03-05T18:05:23.797225"
    },
    {
        "image_name": "img_5.png",
        "x": -11.86337947845459,
        "y": -12.145184516906738,
        "z": -5.483245372772217,
        "yaw": 90.0,
        "timestamp": "2026-03-05T18:05:27.536905"
    },
    {
        "image_name": "img_6.png",
        "x": -11.863314628601074,
        "y": -12.145233154296875,
        "z": -5.484626293182373,
        "yaw": 180.0,
        "timestamp": "2026-03-05T18:05:31.289161"
    },
    {
        "image_name": "img_7.png",
        "x": -11.863314628601074,
        "y": -12.145233154296875,
        "z": -5.485437393188477,
        "yaw": 270.0,
        "timestamp": "2026-03-05T18:05:34.991504"
    },
    {
        "image_name": "img_8.png",
        "x": -0.16128617525100708,
        "y": -15.979317665100098,
        "z": -5.503474712371826,
        "yaw": 0.0,
        "timestamp": "2026-03-05T18:05:46.417764"
    },
    {
        "image_name": "img_9.png",
        "x": -0.1451687067747116,
        "y": -15.987800598144531,
        "z": -5.504289627075195,
        "yaw": 90.0,
        "timestamp": "2026-03-05T18:05:50.143200"
    },
    {
        "image_name": "img_10.png",
        "x": -0.14515943825244904,
        "y": -15.987730026245117,
        "z": -5.5056891441345215,
        "yaw": 180.0,
        "timestamp": "2026-03-05T18:05:53.877402"
    },
    {
        "image_name": "img_11.png",
        "x": -0.14515943825244904,
        "y": -15.987730026245117,
        "z": -5.506496429443359,
        "yaw": 270.0,
        "timestamp": "2026-03-05T18:05:57.584828"
    },
    {
        "image_name": "img_12.png",
        "x": -3.842102527618408,
        "y": -12.169729232788086,
        "z": -5.491509914398193,
        "yaw": 0.0,
        "timestamp": "2026-03-05T18:06:07.361362"
    },
    {
        "image_name": "img_13.png",
        "x": -3.8544533252716064,
        "y": -12.15793514251709,
        "z": -5.492301940917969,
        "yaw": 90.0,
        "timestamp": "2026-03-05T18:06:11.076164"
    },
    {
        "image_name": "img_14.png",
        "x": -3.8544795513153076,
        "y": -12.157991409301758,
        "z": -5.493680477142334,
        "yaw": 180.0,
        "timestamp": "2026-03-05T18:06:14.830242"
    },
    {
        "image_name": "img_15.png",
        "x": -3.8544795513153076,
        "y": -12.157991409301758,
        "z": -5.494490623474121,
        "yaw": 270.0,
        "timestamp": "2026-03-05T18:06:18.540075"
    },
    {
        "image_name": "img_16.png",
        "x": 7.8471293449401855,
        "y": -15.983749389648438,
        "z": -5.516888618469238,
        "yaw": 0.0,
        "timestamp": "2026-03-05T18:06:29.998545"
    },
    {
        "image_name": "img_17.png",
        "x": 7.861530780792236,
        "y": -15.991279602050781,
        "z": -5.517849922180176,
        "yaw": 90.0,
        "timestamp": "2026-03-05T18:06:33.737304"
    },
    {
        "image_name": "img_18.png",
        "x": 7.861512660980225,
        "y": -15.991229057312012,
        "z": -5.519225120544434,
        "yaw": 180.0,
        "timestamp": "2026-03-05T18:06:37.495423"
    },
    {
        "image_name": "img_19.png",
        "x": 7.861512660980225,
        "y": -15.991229057312012,
        "z": -5.52001428604126,
        "yaw": 270.0,
        "timestamp": "2026-03-05T18:06:41.210981"
    },
    {
        "image_name": "img_20.png",
        "x": 4.1870269775390625,
        "y": -12.180890083312988,
        "z": -5.4927778244018555,
        "yaw": 0.0,
        "timestamp": "2026-03-05T18:06:50.967402"
    },
    {
        "image_name": "img_21.png",
        "x": 4.1737871170043945,
        "y": -12.168423652648926,
        "z": -5.4935760498046875,
        "yaw": 90.0,
        "timestamp": "2026-03-05T18:06:54.694319"
    },
    {
        "image_name": "img_22.png",
        "x": 4.173761367797852,
        "y": -12.168484687805176,
        "z": -5.4949541091918945,
        "yaw": 180.0,
        "timestamp": "2026-03-05T18:06:58.452333"
    },
    {
        "image_name": "img_23.png",
        "x": 4.173761367797852,
        "y": -12.168484687805176,
        "z": -5.495843887329102,
        "yaw": 270.0,
        "timestamp": "2026-03-05T18:07:02.162653"
    },
    {
        "image_name": "img_24.png",
        "x": 15.830582618713379,
        "y": -15.975984573364258,
        "z": -5.511911392211914,
        "yaw": 0.0,
        "timestamp": "2026-03-05T18:07:13.566691"
    },
    {
        "image_name": "img_25.png",
        "x": 15.84638786315918,
        "y": -15.984371185302734,
        "z": -5.512722492218018,
        "yaw": 90.0,
        "timestamp": "2026-03-05T18:07:17.296392"
    },
    {
        "image_name": "img_26.png",
        "x": 15.84638786315918,
        "y": -15.984310150146484,
        "z": -5.514089107513428,
        "yaw": 180.0,
        "timestamp": "2026-03-05T18:07:21.061455"
    },
    {
        "image_name": "img_27.png",
        "x": 15.84638786315918,
        "y": -15.984310150146484,
        "z": -5.514881610870361,
        "yaw": 270.0,
        "timestamp": "2026-03-05T18:07:24.772412"
    },
    {
        "image_name": "img_28.png",
        "x": 11.994796752929688,
        "y": -8.161625862121582,
        "z": -5.516983985900879,
        "yaw": 0.0,
        "timestamp": "2026-03-05T18:07:34.425419"
    },
    {
        "image_name": "img_29.png",
        "x": 11.994684219360352,
        "y": -8.145273208618164,
        "z": -5.5178728103637695,
        "yaw": 90.0,
        "timestamp": "2026-03-05T18:07:38.152628"
    },
    {
        "image_name": "img_30.png",
        "x": 11.994629859924316,
        "y": -8.145273208618164,
        "z": -5.519254207611084,
        "yaw": 180.0,
        "timestamp": "2026-03-05T18:07:41.905266"
    },
    {
        "image_name": "img_31.png",
        "x": 11.994629859924316,
        "y": -8.145273208618164,
        "z": -5.520055770874023,
        "yaw": 270.0,
        "timestamp": "2026-03-05T18:07:45.615438"
    },
    {
        "image_name": "img_32.png",
        "x": 4.277614593505859,
        "y": -7.946231365203857,
        "z": -5.502017021179199,
        "yaw": 0.0,
        "timestamp": "2026-03-05T18:07:56.315637"
    },
    {
        "image_name": "img_33.png",
        "x": 4.26338529586792,
        "y": -7.935306072235107,
        "z": -5.502806186676025,
        "yaw": 90.0,
        "timestamp": "2026-03-05T18:08:00.073891"
    },
    {
        "image_name": "img_34.png",
        "x": 4.263368606567383,
        "y": -7.935378074645996,
        "z": -5.504169940948486,
        "yaw": 180.0,
        "timestamp": "2026-03-05T18:08:03.828723"
    },
    {
        "image_name": "img_35.png",
        "x": 4.263368606567383,
        "y": -7.935378074645996,
        "z": -5.50495719909668,
        "yaw": 270.0,
        "timestamp": "2026-03-05T18:08:07.548047"
    },
    {
        "image_name": "img_36.png",
        "x": 0.2549535036087036,
        "y": -8.001885414123535,
        "z": -5.489648818969727,
        "yaw": 0.0,
        "timestamp": "2026-03-05T18:08:18.342254"
    },
    {
        "image_name": "img_37.png",
        "x": 0.23857812583446503,
        "y": -7.9900054931640625,
        "z": -5.490548133850098,
        "yaw": 90.0,
        "timestamp": "2026-03-05T18:08:22.058912"
    },
    {
        "image_name": "img_38.png",
        "x": 0.2385537475347519,
        "y": -7.990090370178223,
        "z": -5.491949558258057,
        "yaw": 180.0,
        "timestamp": "2026-03-05T18:08:25.804203"
    },
    {
        "image_name": "img_39.png",
        "x": 0.2385537475347519,
        "y": -7.990090370178223,
        "z": -5.4928083419799805,
        "yaw": 270.0,
        "timestamp": "2026-03-05T18:08:29.516194"
    },
    {
        "image_name": "img_40.png",
        "x": 0.06550513207912445,
        "y": -4.244609832763672,
        "z": -5.502225399017334,
        "yaw": 0.0,
        "timestamp": "2026-03-05T18:08:41.090661"
    },
    {
        "image_name": "img_41.png",
        "x": 0.06645022332668304,
        "y": -4.224274635314941,
        "z": -5.50302791595459,
        "yaw": 90.0,
        "timestamp": "2026-03-05T18:08:44.847108"
    },
    {
        "image_name": "img_42.png",
        "x": 0.06635089218616486,
        "y": -4.224228858947754,
        "z": -5.504400730133057,
        "yaw": 180.0,
        "timestamp": "2026-03-05T18:08:48.597685"
    },
    {
        "image_name": "img_43.png",
        "x": 0.06635551899671555,
        "y": -4.224228858947754,
        "z": -5.505208969116211,
        "yaw": 270.0,
        "timestamp": "2026-03-05T18:08:52.301515"
    },
    {
        "image_name": "img_44.png",
        "x": -3.997255325317383,
        "y": -19.760772705078125,
        "z": -5.491537094116211,
        "yaw": 0.0,
        "timestamp": "2026-03-05T18:09:05.787607"
    },
    {
        "image_name": "img_45.png",
        "x": -4.002437591552734,
        "y": -19.77654266357422,
        "z": -5.492411136627197,
        "yaw": 90.0,
        "timestamp": "2026-03-05T18:09:09.502756"
    },
    {
        "image_name": "img_46.png",
        "x": -4.002365589141846,
        "y": -19.77654266357422,
        "z": -5.493793964385986,
        "yaw": 180.0,
        "timestamp": "2026-03-05T18:09:13.257603"
    },
    {
        "image_name": "img_47.png",
        "x": -4.002365589141846,
        "y": -19.77654266357422,
        "z": -5.494612693786621,
        "yaw": 270.0,
        "timestamp": "2026-03-05T18:09:16.953181"
    },
    {
        "image_name": "img_48.png",
        "x": -7.921082019805908,
        "y": -8.140899658203125,
        "z": -5.514461994171143,
        "yaw": 0.0,
        "timestamp": "2026-03-05T18:09:28.409456"
    },
    {
        "image_name": "img_49.png",
        "x": -7.923769474029541,
        "y": -8.125398635864258,
        "z": -5.515349864959717,
        "yaw": 90.0,
        "timestamp": "2026-03-05T18:09:32.103372"
    },
    {
        "image_name": "img_50.png",
        "x": -7.923828125,
        "y": -8.125357627868652,
        "z": -5.516751766204834,
        "yaw": 180.0,
        "timestamp": "2026-03-05T18:09:35.848996"
    },
    {
        "image_name": "img_51.png",
        "x": -7.923828125,
        "y": -8.125357627868652,
        "z": -5.517567157745361,
        "yaw": 270.0,
        "timestamp": "2026-03-05T18:09:39.548926"
    },
    {
        "image_name": "img_52.png",
        "x": -15.848123550415039,
        "y": -15.805410385131836,
        "z": -5.5108418464660645,
        "yaw": 0.0,
        "timestamp": "2026-03-05T18:09:50.374344"
    },
    {
        "image_name": "img_53.png",
        "x": -15.861749649047852,
        "y": -15.815619468688965,
        "z": -5.511878967285156,
        "yaw": 90.0,
        "timestamp": "2026-03-05T18:09:54.056174"
    },
    {
        "image_name": "img_54.png",
        "x": -15.861706733703613,
        "y": -15.815591812133789,
        "z": -5.513277530670166,
        "yaw": 180.0,
        "timestamp": "2026-03-05T18:09:57.810128"
    },
    {
        "image_name": "img_55.png",
        "x": -15.861706733703613,
        "y": -15.815591812133789,
        "z": -5.514087200164795,
        "yaw": 270.0,
        "timestamp": "2026-03-05T18:10:01.514635"
    },
    {
        "image_name": "img_56.png",
        "x": -19.751646041870117,
        "y": -12.068392753601074,
        "z": -5.49511194229126,
        "yaw": 0.0,
        "timestamp": "2026-03-05T18:10:12.714579"
    },
    {
        "image_name": "img_57.png",
        "x": -19.77057456970215,
        "y": -12.067472457885742,
        "z": -5.495971202850342,
        "yaw": 90.0,
        "timestamp": "2026-03-05T18:10:16.473589"
    },
    {
        "image_name": "img_58.png",
        "x": -19.77057456970215,
        "y": -12.067547798156738,
        "z": -5.4973249435424805,
        "yaw": 180.0,
        "timestamp": "2026-03-05T18:10:20.245097"
    },
    {
        "image_name": "img_59.png",
        "x": -19.77057456970215,
        "y": -12.067547798156738,
        "z": -5.4981207847595215,
        "yaw": 270.0,
        "timestamp": "2026-03-05T18:10:23.965479"
    },
    {
        "image_name": "img_60.png",
        "x": -15.650874137878418,
        "y": -4.007113933563232,
        "z": -5.508734226226807,
        "yaw": 0.0,
        "timestamp": "2026-03-05T18:10:34.630475"
    },
    {
        "image_name": "img_61.png",
        "x": -15.663786888122559,
        "y": -3.9937474727630615,
        "z": -5.509521007537842,
        "yaw": 90.0,
        "timestamp": "2026-03-05T18:10:38.370422"
    },
    {
        "image_name": "img_62.png",
        "x": -15.663680076599121,
        "y": -3.9938247203826904,
        "z": -5.510904312133789,
        "yaw": 180.0,
        "timestamp": "2026-03-05T18:10:42.118362"
    },
    {
        "image_name": "img_63.png",
        "x": -15.663680076599121,
        "y": -3.9938247203826904,
        "z": -5.511710166931152,
        "yaw": 270.0,
        "timestamp": "2026-03-05T18:10:45.826447"
    },
    {
        "image_name": "img_64.png",
        "x": -8.081974029541016,
        "y": -4.153073787689209,
        "z": -5.4957356452941895,
        "yaw": 0.0,
        "timestamp": "2026-03-05T18:10:56.567899"
    },
    {
        "image_name": "img_65.png",
        "x": -8.070487976074219,
        "y": -4.138484477996826,
        "z": -5.4967193603515625,
        "yaw": 90.0,
        "timestamp": "2026-03-05T18:11:00.255159"
    },
    {
        "image_name": "img_66.png",
        "x": -8.070552825927734,
        "y": -4.138464450836182,
        "z": -5.498111724853516,
        "yaw": 180.0,
        "timestamp": "2026-03-05T18:11:04.019895"
    },
    {
        "image_name": "img_67.png",
        "x": -8.070552825927734,
        "y": -4.138464450836182,
        "z": -5.498933792114258,
        "yaw": 270.0,
        "timestamp": "2026-03-05T18:11:07.716503"
    },
    {
        "image_name": "img_68.png",
        "x": -7.943445205688477,
        "y": -0.21056662499904633,
        "z": -5.487159252166748,
        "yaw": 0.0,
        "timestamp": "2026-03-05T18:11:19.327435"
    },
    {
        "image_name": "img_69.png",
        "x": -7.943323135375977,
        "y": -0.1927025020122528,
        "z": -5.487795829772949,
        "yaw": 90.0,
        "timestamp": "2026-03-05T18:11:23.102480"
    },
    {
        "image_name": "img_70.png",
        "x": -7.943384647369385,
        "y": -0.19273315370082855,
        "z": -5.489092826843262,
        "yaw": 180.0,
        "timestamp": "2026-03-05T18:11:26.844439"
    },
    {
        "image_name": "img_71.png",
        "x": -7.943384647369385,
        "y": -0.1927332729101181,
        "z": -5.489896774291992,
        "yaw": 270.0,
        "timestamp": "2026-03-05T18:11:30.640347"
    },
    {
        "image_name": "img_72.png",
        "x": -3.954068899154663,
        "y": -0.24804671108722687,
        "z": -5.477964401245117,
        "yaw": 0.0,
        "timestamp": "2026-03-05T18:11:44.936931"
    },
    {
        "image_name": "img_73.png",
        "x": -3.952406406402588,
        "y": -0.22838282585144043,
        "z": -5.478776931762695,
        "yaw": 90.0,
        "timestamp": "2026-03-05T18:11:48.687612"
    },
    {
        "image_name": "img_74.png",
        "x": -3.9524998664855957,
        "y": -0.22841259837150574,
        "z": -5.480153560638428,
        "yaw": 180.0,
        "timestamp": "2026-03-05T18:11:52.459232"
    },
    {
        "image_name": "img_75.png",
        "x": -3.9524998664855957,
        "y": -0.22841274738311768,
        "z": -5.480956077575684,
        "yaw": 270.0,
        "timestamp": "2026-03-05T18:11:56.173582"
    },
    {
        "image_name": "img_76.png",
        "x": 3.9266061782836914,
        "y": -19.77031707763672,
        "z": -5.5063347816467285,
        "yaw": 0.0,
        "timestamp": "2026-03-05T18:12:12.451006"
    },
    {
        "image_name": "img_77.png",
        "x": 3.9277658462524414,
        "y": -19.78836441040039,
        "z": -5.507216453552246,
        "yaw": 90.0,
        "timestamp": "2026-03-05T18:12:16.144367"
    },
    {
        "image_name": "img_78.png",
        "x": 3.927849292755127,
        "y": -19.78836441040039,
        "z": -5.508597373962402,
        "yaw": 180.0,
        "timestamp": "2026-03-05T18:12:19.914938"
    },
    {
        "image_name": "img_79.png",
        "x": 3.927849292755127,
        "y": -19.78836441040039,
        "z": -5.5093865394592285,
        "yaw": 270.0,
        "timestamp": "2026-03-05T18:12:23.635571"
    },
    {
        "image_name": "img_80.png",
        "x": 11.847947120666504,
        "y": -4.233215808868408,
        "z": -5.506806373596191,
        "yaw": 0.0,
        "timestamp": "2026-03-05T18:12:39.698374"
    },
    {
        "image_name": "img_81.png",
        "x": 11.86797046661377,
        "y": -4.226011753082275,
        "z": -5.507741451263428,
        "yaw": 90.0,
        "timestamp": "2026-03-05T18:12:43.466161"
    },
    {
        "image_name": "img_82.png",
        "x": 11.867956161499023,
        "y": -4.225944995880127,
        "z": -5.509097576141357,
        "yaw": 180.0,
        "timestamp": "2026-03-05T18:12:47.238866"
    },
    {
        "image_name": "img_83.png",
        "x": 11.867956161499023,
        "y": -4.225944995880127,
        "z": -5.509946346282959,
        "yaw": 270.0,
        "timestamp": "2026-03-05T18:12:50.960941"
    },
    {
        "image_name": "img_84.png",
        "x": 15.75320816040039,
        "y": -7.949349403381348,
        "z": -5.4851202964782715,
        "yaw": 0.0,
        "timestamp": "2026-03-05T18:13:02.906221"
    },
    {
        "image_name": "img_85.png",
        "x": 15.769102096557617,
        "y": -7.955459117889404,
        "z": -5.486035346984863,
        "yaw": 90.0,
        "timestamp": "2026-03-05T18:13:06.672222"
    },
    {
        "image_name": "img_86.png",
        "x": 15.769102096557617,
        "y": -7.955386161804199,
        "z": -5.487420082092285,
        "yaw": 180.0,
        "timestamp": "2026-03-05T18:13:10.446451"
    },
    {
        "image_name": "img_87.png",
        "x": 15.769102096557617,
        "y": -7.955386161804199,
        "z": -5.488220691680908,
        "yaw": 270.0,
        "timestamp": "2026-03-05T18:13:14.159039"
    },
    {
        "image_name": "img_88.png",
        "x": 12.196772575378418,
        "y": -0.2063271701335907,
        "z": -5.510799884796143,
        "yaw": 0.0,
        "timestamp": "2026-03-05T18:13:24.791363"
    },
    {
        "image_name": "img_89.png",
        "x": 12.194169998168945,
        "y": -0.18665632605552673,
        "z": -5.511692047119141,
        "yaw": 90.0,
        "timestamp": "2026-03-05T18:13:28.468858"
    },
    {
        "image_name": "img_90.png",
        "x": 12.194098472595215,
        "y": -0.18671225011348724,
        "z": -5.513096332550049,
        "yaw": 180.0,
        "timestamp": "2026-03-05T18:13:32.224320"
    },
    {
        "image_name": "img_91.png",
        "x": 12.194098472595215,
        "y": -0.1867099553346634,
        "z": -5.514005661010742,
        "yaw": 270.0,
        "timestamp": "2026-03-05T18:13:35.916789"
    },
    {
        "image_name": "img_92.png",
        "x": 15.786728858947754,
        "y": -0.11299730092287064,
        "z": -5.511714935302734,
        "yaw": 0.0,
        "timestamp": "2026-03-05T18:13:45.686723"
    },
    {
        "image_name": "img_93.png",
        "x": 15.80221176147461,
        "y": -0.10211829841136932,
        "z": -5.512641429901123,
        "yaw": 90.0,
        "timestamp": "2026-03-05T18:13:49.438487"
    },
    {
        "image_name": "img_94.png",
        "x": 15.802160263061523,
        "y": -0.10206873714923859,
        "z": -5.514007568359375,
        "yaw": 180.0,
        "timestamp": "2026-03-05T18:13:53.187853"
    },
    {
        "image_name": "img_95.png",
        "x": 15.802160263061523,
        "y": -0.10207101702690125,
        "z": -5.514827251434326,
        "yaw": 270.0,
        "timestamp": "2026-03-05T18:13:56.895084"
    },
    {
        "image_name": "img_96.png",
        "x": 11.96325397491455,
        "y": 3.752765655517578,
        "z": -5.507270336151123,
        "yaw": 0.0,
        "timestamp": "2026-03-05T18:14:10.920041"
    },
    {
        "image_name": "img_97.png",
        "x": 11.971039772033691,
        "y": 3.76682186126709,
        "z": -5.508270263671875,
        "yaw": 90.0,
        "timestamp": "2026-03-05T18:14:14.616883"
    },
    {
        "image_name": "img_98.png",
        "x": 11.970985412597656,
        "y": 3.7668161392211914,
        "z": -5.509674072265625,
        "yaw": 180.0,
        "timestamp": "2026-03-05T18:14:18.361600"
    },
    {
        "image_name": "img_99.png",
        "x": 11.970985412597656,
        "y": 3.7668161392211914,
        "z": -5.510456562042236,
        "yaw": 270.0,
        "timestamp": "2026-03-05T18:14:22.080396"
    },
    {
        "image_name": "img_100.png",
        "x": 4.046933650970459,
        "y": -0.1616387963294983,
        "z": -5.497565746307373,
        "yaw": 0.0,
        "timestamp": "2026-03-05T18:14:34.837358"
    },
    {
        "image_name": "img_101.png",
        "x": 4.048590660095215,
        "y": -0.14606410264968872,
        "z": -5.49818754196167,
        "yaw": 90.0,
        "timestamp": "2026-03-05T18:14:38.620661"
    },
    {
        "image_name": "img_102.png",
        "x": 4.048534870147705,
        "y": -0.14608649909496307,
        "z": -5.4994797706604,
        "yaw": 180.0,
        "timestamp": "2026-03-05T18:14:42.371866"
    },
    {
        "image_name": "img_103.png",
        "x": 4.048534870147705,
        "y": -0.14608649909496307,
        "z": -5.500357151031494,
        "yaw": 270.0,
        "timestamp": "2026-03-05T18:14:46.089622"
    },
    {
        "image_name": "img_104.png",
        "x": -3.808023452758789,
        "y": 3.8341472148895264,
        "z": -5.511557579040527,
        "yaw": 0.0,
        "timestamp": "2026-03-05T18:14:58.617408"
    },
    {
        "image_name": "img_105.png",
        "x": -3.8194785118103027,
        "y": 3.852695941925049,
        "z": -5.512148857116699,
        "yaw": 90.0,
        "timestamp": "2026-03-05T18:15:02.392283"
    },
    {
        "image_name": "img_106.png",
        "x": -3.819533109664917,
        "y": 3.8526217937469482,
        "z": -5.513454437255859,
        "yaw": 180.0,
        "timestamp": "2026-03-05T18:15:06.135048"
    },
    {
        "image_name": "img_107.png",
        "x": -3.819533109664917,
        "y": 3.8526217937469482,
        "z": -5.514241695404053,
        "yaw": 270.0,
        "timestamp": "2026-03-05T18:15:09.866293"
    },
    {
        "image_name": "img_108.png",
        "x": -11.762397766113281,
        "y": -0.06474269926548004,
        "z": -5.487667083740234,
        "yaw": 0.0,
        "timestamp": "2026-03-05T18:15:24.424636"
    },
    {
        "image_name": "img_109.png",
        "x": -11.778670310974121,
        "y": -0.05601261183619499,
        "z": -5.488611698150635,
        "yaw": 90.0,
        "timestamp": "2026-03-05T18:15:28.117260"
    },
    {
        "image_name": "img_110.png",
        "x": -11.778670310974121,
        "y": -0.05610337108373642,
        "z": -5.4900031089782715,
        "yaw": 180.0,
        "timestamp": "2026-03-05T18:15:31.863671"
    },
    {
        "image_name": "img_111.png",
        "x": -11.778670310974121,
        "y": -0.05610021948814392,
        "z": -5.490874290466309,
        "yaw": 270.0,
        "timestamp": "2026-03-05T18:15:35.599907"
    },
    {
        "image_name": "img_112.png",
        "x": -11.82440185546875,
        "y": 3.8341219425201416,
        "z": -5.498570919036865,
        "yaw": 0.0,
        "timestamp": "2026-03-05T18:15:49.302818"
    },
    {
        "image_name": "img_113.png",
        "x": -11.833498001098633,
        "y": 3.851372480392456,
        "z": -5.499152183532715,
        "yaw": 90.0,
        "timestamp": "2026-03-05T18:15:53.078947"
    },
    {
        "image_name": "img_114.png",
        "x": -11.833529472351074,
        "y": 3.8513081073760986,
        "z": -5.500431537628174,
        "yaw": 180.0,
        "timestamp": "2026-03-05T18:15:56.825501"
    },
    {
        "image_name": "img_115.png",
        "x": -11.833529472351074,
        "y": 3.8513081073760986,
        "z": -5.501219272613525,
        "yaw": 270.0,
        "timestamp": "2026-03-05T18:16:00.549392"
    },
    {
        "image_name": "img_116.png",
        "x": -19.78107261657715,
        "y": -3.931462287902832,
        "z": -5.5101823806762695,
        "yaw": 0.0,
        "timestamp": "2026-03-05T18:16:14.658217"
    },
    {
        "image_name": "img_117.png",
        "x": -19.79798126220703,
        "y": -3.9314382076263428,
        "z": -5.511058807373047,
        "yaw": 90.0,
        "timestamp": "2026-03-05T18:16:18.399648"
    },
    {
        "image_name": "img_118.png",
        "x": -19.79798126220703,
        "y": -3.9315152168273926,
        "z": -5.512432098388672,
        "yaw": 180.0,
        "timestamp": "2026-03-05T18:16:22.161514"
    },
    {
        "image_name": "img_119.png",
        "x": -19.79798126220703,
        "y": -3.9315152168273926,
        "z": -5.513332366943359,
        "yaw": 270.0,
        "timestamp": "2026-03-05T18:16:25.861972"
    },
    {
        "image_name": "img_120.png",
        "x": -19.828746795654297,
        "y": -0.16440801322460175,
        "z": -5.489952087402344,
        "yaw": 0.0,
        "timestamp": "2026-03-05T18:16:37.590437"
    },
    {
        "image_name": "img_121.png",
        "x": -19.840660095214844,
        "y": -0.1509622037410736,
        "z": -5.490747451782227,
        "yaw": 90.0,
        "timestamp": "2026-03-05T18:16:41.359794"
    },
    {
        "image_name": "img_122.png",
        "x": -19.840660095214844,
        "y": -0.15103663504123688,
        "z": -5.49211311340332,
        "yaw": 180.0,
        "timestamp": "2026-03-05T18:16:45.113591"
    },
    {
        "image_name": "img_123.png",
        "x": -19.840660095214844,
        "y": -0.1510334014892578,
        "z": -5.492908000946045,
        "yaw": 270.0,
        "timestamp": "2026-03-05T18:16:48.832935"
    },
    {
        "image_name": "img_124.png",
        "x": -19.82452964782715,
        "y": 3.8271498680114746,
        "z": -5.484344005584717,
        "yaw": 0.0,
        "timestamp": "2026-03-05T18:17:00.627937"
    },
    {
        "image_name": "img_125.png",
        "x": -19.837268829345703,
        "y": 3.840165853500366,
        "z": -5.485123157501221,
        "yaw": 90.0,
        "timestamp": "2026-03-05T18:17:04.356853"
    },
    {
        "image_name": "img_126.png",
        "x": -19.837268829345703,
        "y": 3.8400917053222656,
        "z": -5.486505031585693,
        "yaw": 180.0,
        "timestamp": "2026-03-05T18:17:08.107519"
    },
    {
        "image_name": "img_127.png",
        "x": -19.837268829345703,
        "y": 3.8400917053222656,
        "z": -5.487316131591797,
        "yaw": 270.0,
        "timestamp": "2026-03-05T18:17:11.815645"
    },
    {
        "image_name": "img_128.png",
        "x": -12.023038864135742,
        "y": 7.752096176147461,
        "z": -5.485860347747803,
        "yaw": 0.0,
        "timestamp": "2026-03-05T18:17:26.314281"
    },
    {
        "image_name": "img_129.png",
        "x": -12.020438194274902,
        "y": 7.769082546234131,
        "z": -5.486719608306885,
        "yaw": 90.0,
        "timestamp": "2026-03-05T18:17:30.050154"
    },
    {
        "image_name": "img_130.png",
        "x": -12.020496368408203,
        "y": 7.769086837768555,
        "z": -5.4881086349487305,
        "yaw": 180.0,
        "timestamp": "2026-03-05T18:17:33.793959"
    },
    {
        "image_name": "img_131.png",
        "x": -12.020496368408203,
        "y": 7.769086837768555,
        "z": -5.488932132720947,
        "yaw": 270.0,
        "timestamp": "2026-03-05T18:17:37.484613"
    },
    {
        "image_name": "img_132.png",
        "x": -7.95594596862793,
        "y": 7.755418300628662,
        "z": -5.4930877685546875,
        "yaw": 0.0,
        "timestamp": "2026-03-05T18:17:51.779589"
    },
    {
        "image_name": "img_133.png",
        "x": -7.9541802406311035,
        "y": 7.775620460510254,
        "z": -5.493880271911621,
        "yaw": 90.0,
        "timestamp": "2026-03-05T18:17:55.568536"
    },
    {
        "image_name": "img_134.png",
        "x": -7.954265117645264,
        "y": 7.775649547576904,
        "z": -5.495251178741455,
        "yaw": 180.0,
        "timestamp": "2026-03-05T18:17:59.322295"
    },
    {
        "image_name": "img_135.png",
        "x": -7.954265117645264,
        "y": 7.775649547576904,
        "z": -5.496060848236084,
        "yaw": 270.0,
        "timestamp": "2026-03-05T18:18:03.026117"
    },
    {
        "image_name": "img_136.png",
        "x": -0.157065749168396,
        "y": 3.859856605529785,
        "z": -5.492868900299072,
        "yaw": 0.0,
        "timestamp": "2026-03-05T18:18:15.479098"
    },
    {
        "image_name": "img_137.png",
        "x": -0.14364850521087646,
        "y": 3.874065637588501,
        "z": -5.493865966796875,
        "yaw": 90.0,
        "timestamp": "2026-03-05T18:18:19.170023"
    },
    {
        "image_name": "img_138.png",
        "x": -0.14374133944511414,
        "y": 3.874098062515259,
        "z": -5.495172500610352,
        "yaw": 180.0,
        "timestamp": "2026-03-05T18:18:22.979758"
    },
    {
        "image_name": "img_139.png",
        "x": -0.14373718202114105,
        "y": 3.874098062515259,
        "z": -5.495954513549805,
        "yaw": 270.0,
        "timestamp": "2026-03-05T18:18:26.706111"
    },
    {
        "image_name": "img_140.png",
        "x": 0.06071462109684944,
        "y": 7.754788398742676,
        "z": -5.47606086730957,
        "yaw": 0.0,
        "timestamp": "2026-03-05T18:18:38.302668"
    },
    {
        "image_name": "img_141.png",
        "x": 0.06098315864801407,
        "y": 7.770486831665039,
        "z": -5.4766950607299805,
        "yaw": 90.0,
        "timestamp": "2026-03-05T18:18:42.076372"
    },
    {
        "image_name": "img_142.png",
        "x": 0.06091534346342087,
        "y": 7.770534992218018,
        "z": -5.477982044219971,
        "yaw": 180.0,
        "timestamp": "2026-03-05T18:18:45.836744"
    },
    {
        "image_name": "img_143.png",
        "x": 0.06091791391372681,
        "y": 7.770534992218018,
        "z": -5.4787797927856445,
        "yaw": 270.0,
        "timestamp": "2026-03-05T18:18:49.549676"
    },
    {
        "image_name": "img_144.png",
        "x": 7.852823257446289,
        "y": 3.8884658813476562,
        "z": -5.50909423828125,
        "yaw": 0.0,
        "timestamp": "2026-03-05T18:19:01.952711"
    },
    {
        "image_name": "img_145.png",
        "x": 7.866143703460693,
        "y": 3.9005041122436523,
        "z": -5.509981632232666,
        "yaw": 90.0,
        "timestamp": "2026-03-05T18:19:05.714994"
    },
    {
        "image_name": "img_146.png",
        "x": 7.8660783767700195,
        "y": 3.900535821914673,
        "z": -5.511343955993652,
        "yaw": 180.0,
        "timestamp": "2026-03-05T18:19:09.476932"
    },
    {
        "image_name": "img_147.png",
        "x": 7.8660783767700195,
        "y": 3.900535821914673,
        "z": -5.512212753295898,
        "yaw": 270.0,
        "timestamp": "2026-03-05T18:19:13.195011"
    },
    {
        "image_name": "img_148.png",
        "x": 8.060835838317871,
        "y": 7.753496170043945,
        "z": -5.49057149887085,
        "yaw": 0.0,
        "timestamp": "2026-03-05T18:19:24.745454"
    },
    {
        "image_name": "img_149.png",
        "x": 8.062067031860352,
        "y": 7.772153377532959,
        "z": -5.491368770599365,
        "yaw": 90.0,
        "timestamp": "2026-03-05T18:19:28.525213"
    },
    {
        "image_name": "img_150.png",
        "x": 8.06200122833252,
        "y": 7.772192001342773,
        "z": -5.492717742919922,
        "yaw": 180.0,
        "timestamp": "2026-03-05T18:19:32.300666"
    },
    {
        "image_name": "img_151.png",
        "x": 8.06200122833252,
        "y": 7.772192001342773,
        "z": -5.4936065673828125,
        "yaw": 270.0,
        "timestamp": "2026-03-05T18:19:36.010017"
    },
    {
        "image_name": "img_152.png",
        "x": 19.760009765625,
        "y": 0.12170042097568512,
        "z": -5.488476276397705,
        "yaw": 0.0,
        "timestamp": "2026-03-05T18:19:49.213259"
    },
    {
        "image_name": "img_153.png",
        "x": 19.77743148803711,
        "y": 0.11360275000333786,
        "z": -5.4896650314331055,
        "yaw": 90.0,
        "timestamp": "2026-03-05T18:19:52.855433"
    },
    {
        "image_name": "img_154.png",
        "x": 19.77743148803711,
        "y": 0.11370429396629333,
        "z": -5.4913330078125,
        "yaw": 180.0,
        "timestamp": "2026-03-05T18:19:56.548121"
    },
    {
        "image_name": "img_155.png",
        "x": 19.77743148803711,
        "y": 0.11369870603084564,
        "z": -5.492344856262207,
        "yaw": 270.0,
        "timestamp": "2026-03-05T18:20:00.214409"
    }
]